qds/__init__.py
qds/bindings.py
qds/lib.py
qds/lib.pyi
python_qds-0.1.0.dist-info/LICENSE.md
python_qds-0.1.0.dist-info/WHEEL
python_qds-0.1.0.dist-info/METADATA
python_qds-0.1.0.dist-info/RECORD
